movinets_helper/__init__.py
movinets_helper/modeling.py
movinets_helper/reader.py
movinets_helper/utils.py
movinets_helper/writer.py
movinets_helper-0.1.5.dist-info/LICENSE
movinets_helper-0.1.5.dist-info/WHEEL
movinets_helper-0.1.5.dist-info/METADATA
movinets_helper-0.1.5.dist-info/RECORD
