Metadata-Version: 2.1
Name: movinets_helper
Version: 0.1.5
Summary: Package to help fine-tuning MoViNets.
Home-page: https://github.com/plaguss/movinets_helper
License: MIT
Author: Agustín Piqueres
Author-email: agustin.piqueres@gmail.com
Requires-Python: >=3.7
Classifier: Intended Audience :: Developers
Classifier: License :: OSI Approved :: MIT License
Classifier: Programming Language :: Python :: 3.7
Classifier: Programming Language :: Python :: 3.8
Requires-Dist: tensorflow
Requires-Dist: tensorflow-io>=0.26.0
Requires-Dist: tf-models-official
Requires-Dist: tensorflow-hub
Requires-Dist: tqdm>=4.62.3
Requires-Dist: pandas>=1.3.5
Requires-Dist: opencv-python>=4.5.5.62
Requires-Dist: opencv-python-headless>=4.6.0.66
Requires-Dist: isort ; extra == "dev"
Requires-Dist: black ; extra == "dev"
Requires-Dist: mypy ; extra == "dev"
Requires-Dist: nox ; extra == "dev"
Requires-Dist: flake8 ; extra == "dev"
Requires-Dist: mkdocs ; extra == "doc"
Requires-Dist: mkdocs-material ; extra == "doc"
Requires-Dist: mkdocstrings[python] ; extra == "doc"
Requires-Dist: pytest==6.2.3 ; extra == "test"
Requires-Dist: pytest-cov==2.11.1 ; extra == "test"
Project-URL: Documentation, https://plaguss.github.io/movinets_helper/
Project-URL: Repository, https://github.com/plaguss/movinets_helper
Provides-Extra: dev
Provides-Extra: doc
Provides-Extra: test
